{
    "@class": "com.kony.gen.viz.model.component.KVizLabel",
    "DNDConfig": null,
    "__parentReadjusting__": false,
    "_height_": {
        "type": "ref",
        "value": "preferred"
    },
    "_left_": {
        "type": "string",
        "value": "0dp"
    },
    "_margin_": [
        1,
        1,
        1,
        1
    ],
    "_padding_": [
        0,
        0,
        0,
        0
    ],
    "_skin_": "sc062f761a04421f87ba46b085ca5649",
    "_text_": "STO Telkom Kemayoran",
    "_top_": {
        "type": "string",
        "value": "0dp"
    },
    "_width_": {
        "type": "ref",
        "value": "preferred"
    },
    "_wrapping_": 2,
    "android": {
        "textStyle": {
            "letterSpacing": 0,
            "strikeThrough": false
        }
    },
    "canUpdateUI": true,
    "centery": {
        "type": "string",
        "value": "50%"
    },
    "containerweight": 100,
    "contentalignment": 4,
    "id": "CopyLabelNamaBest0i1befb6a94e346",
    "info": null,
    "ipad": {
        "psp": {
            "wrapping": 2
        }
    },
    "iphone": {
        "psp": {
            "wrapping": 2
        }
    },
    "isvisible": true,
    "kuid": "feb91440e7694a199e95fbabd9370f94",
    "name": "kony.ui.Label",
    "parent": "CopyFlexNamaBest0ia89b2c4b8164e",
    "pf": "FormLeaderboard",
    "tooltip": "",
    "wType": "Label",
    "zindex": 1
}